setup.py
awstrust/__init__.py
awstrust.egg-info/PKG-INFO
awstrust.egg-info/SOURCES.txt
awstrust.egg-info/dependency_links.txt
awstrust.egg-info/requires.txt
awstrust.egg-info/top_level.txt
awstrust.egg-info/zip-safe