Metadata-Version: 1.0
Name: awstrust
Version: 0.2.1
Summary: Library for verifying AWS Instance Identity Documents
Home-page: https://github.com/heph/awstrust
Author: Stephen H. Adams
Author-email: steve@steveadams.io
License: Apache License 2.0
Platform: UNKNOWN
